src/__init__.py
src/upconan.py
upconan-1.0.9.dist-info/LICENSE
upconan-1.0.9.dist-info/METADATA
upconan-1.0.9.dist-info/WHEEL
upconan-1.0.9.dist-info/entry_points.txt
upconan-1.0.9.dist-info/top_level.txt
upconan-1.0.9.dist-info/RECORD
