Metadata-Version: 2.1
Name: upconan
Version: 1.0.9
Summary: 一个更新conanfile的便捷工具
Home-page: https://github.com/leytou/upconan
Author: leytou
Author-email: hi_litao@163.com
License: MIT
Keywords: python conan
Classifier: Programming Language :: Python :: 3
Requires-Python: >=3.7
License-File: LICENSE
Requires-Dist: GitPython
Requires-Dist: pyperclip
